ovos_m2v_pipeline/__init__.py
ovos_m2v_pipeline/version.py
ovos_m2v_pipeline-0.0.7.dist-info/METADATA
ovos_m2v_pipeline-0.0.7.dist-info/WHEEL
ovos_m2v_pipeline-0.0.7.dist-info/entry_points.txt
ovos_m2v_pipeline-0.0.7.dist-info/top_level.txt
ovos_m2v_pipeline-0.0.7.dist-info/RECORD
